[{"lon":18.97,"lat":47.41},{"lon":19.02,"lat":47.41},{"lon":19.08,"lat":47.41},{"lon":19.13,"lat":47.41},{"lon":19.19,"lat":47.41},{"lon":19.24,"lat":47.41},{"lon":18.97,"lat":47.43},{"lon":19.02,"lat":47.43},{"lon":19.08,"lat":47.43},{"lon":19.13,"lat":47.43},{"lon":19.19,"lat":47.43},{"lon":19.24,"lat":47.43},{"lon":18.97,"lat":47.45},{"lon":19.02,"lat":47.45},{"lon":19.08,"lat":47.45},{"lon":19.13,"lat":47.45},{"lon":19.19,"lat":47.45},{"lon":19.24,"lat":47.45},{"lon":18.97,"lat":47.47},{"lon":19.02,"lat":47.47},{"lon":19.08,"lat":47.47},{"lon":19.13,"lat":47.47},{"lon":19.19,"lat":47.47},{"lon":19.24,"lat":47.47},{"lon":18.97,"lat":47.49},{"lon":19.02,"lat":47.49},{"lon":19.08,"lat":47.49},{"lon":19.13,"lat":47.49},{"lon":19.19,"lat":47.49},{"lon":19.24,"lat":47.49},{"lon":18.97,"lat":47.5},{"lon":19.02,"lat":47.5},{"lon":19.08,"lat":47.5},{"lon":19.13,"lat":47.5},{"lon":19.19,"lat":47.5},{"lon":19.24,"lat":47.5},{"lon":18.97,"lat":47.52},{"lon":19.02,"lat":47.52},{"lon":19.08,"lat":47.52},{"lon":19.13,"lat":47.52},{"lon":19.19,"lat":47.52},{"lon":19.24,"lat":47.52},{"lon":18.97,"lat":47.54},{"lon":19.02,"lat":47.54},{"lon":19.08,"lat":47.54},{"lon":19.13,"lat":47.54},{"lon":19.19,"lat":47.54},{"lon":19.24,"lat":47.54},{"lon":18.97,"lat":47.56},{"lon":19.02,"lat":47.56},{"lon":19.08,"lat":47.56},{"lon":19.13,"lat":47.56},{"lon":19.19,"lat":47.56},{"lon":19.24,"lat":47.56},{"lon":18.97,"lat":47.58},{"lon":19.02,"lat":47.58},{"lon":19.08,"lat":47.58},{"lon":19.13,"lat":47.58},{"lon":19.19,"lat":47.58},{"lon":19.24,"lat":47.58}]